{
	"hitboxes": [
		{
			"tl": {
				"x": 143,
				"y": 76
			},
			"tr": {
				"x": 227,
				"y": 76
			},
			"br": {
				"x": 227,
				"y": 144
			},
			"bl": {
				"x": 143,
				"y": 144
			}
		},
		{
			"tl": {
				"x": 221,
				"y": 106
			},
			"tr": {
				"x": 227,
				"y": 106
			},
			"br": {
				"x": 227,
				"y": 144
			},
			"bl": {
				"x": 221,
				"y": 144
			}
		},
		{
			"tl": {
				"x": 221,
				"y": 106
			},
			"tr": {
				"x": 267,
				"y": 106
			},
			"br": {
				"x": 267,
				"y": 144
			},
			"bl": {
				"x": 221,
				"y": 144
			}
		},
		{
			"tl": {
				"x": 227,
				"y": 106
			},
			"tr": {
				"x": 267,
				"y": 106
			},
			"br": {
				"x": 267,
				"y": 144
			},
			"bl": {
				"x": 227,
				"y": 144
			}
		}
	],
	"hurtboxes": [
		{
			"tl": {
				"x": 87,
				"y": 34
			},
			"tr": {
				"x": 171,
				"y": 34
			},
			"br": {
				"x": 171,
				"y": 142
			},
			"bl": {
				"x": 87,
				"y": 142
			}
		},
		{
			"tl": {
				"x": 157,
				"y": 62
			},
			"tr": {
				"x": 171,
				"y": 62
			},
			"br": {
				"x": 171,
				"y": 142
			},
			"bl": {
				"x": 157,
				"y": 142
			}
		},
		{
			"tl": {
				"x": 157,
				"y": 62
			},
			"tr": {
				"x": 201,
				"y": 62
			},
			"br": {
				"x": 201,
				"y": 144
			},
			"bl": {
				"x": 157,
				"y": 144
			}
		}
	]
}