{
	"hitboxes": [
		{
			"tl": {
				"x": 67,
				"y": 82
			},
			"tr": {
				"x": 99,
				"y": 82
			},
			"br": {
				"x": 99,
				"y": 144
			},
			"bl": {
				"x": 67,
				"y": 144
			}
		},
		{
			"tl": {
				"x": 99,
				"y": 140
			},
			"tr": {
				"x": 125,
				"y": 140
			},
			"br": {
				"x": 125,
				"y": 188
			},
			"bl": {
				"x": 99,
				"y": 188
			}
		}
	],
	"hurtboxes": [
		{
			"tl": {
				"x": 7,
				"y": 4
			},
			"tr": {
				"x": 71,
				"y": 4
			},
			"br": {
				"x": 71,
				"y": 88
			},
			"bl": {
				"x": 7,
				"y": 88
			}
		},
		{
			"tl": {
				"x": 21,
				"y": 76
			},
			"tr": {
				"x": 71,
				"y": 76
			},
			"br": {
				"x": 71,
				"y": 88
			},
			"bl": {
				"x": 21,
				"y": 88
			}
		},
		{
			"tl": {
				"x": 21,
				"y": 76
			},
			"tr": {
				"x": 107,
				"y": 76
			},
			"br": {
				"x": 107,
				"y": 150
			},
			"bl": {
				"x": 21,
				"y": 150
			}
		},
		{
			"tl": {
				"x": 87,
				"y": 128
			},
			"tr": {
				"x": 107,
				"y": 128
			},
			"br": {
				"x": 107,
				"y": 150
			},
			"bl": {
				"x": 87,
				"y": 150
			}
		},
		{
			"tl": {
				"x": 87,
				"y": 128
			},
			"tr": {
				"x": 135,
				"y": 128
			},
			"br": {
				"x": 135,
				"y": 200
			},
			"bl": {
				"x": 87,
				"y": 200
			}
		}
	]
}