{
	"hitboxes": [
		{
			"tl": {
				"x": 105,
				"y": 10
			},
			"tr": {
				"x": 141,
				"y": 10
			},
			"br": {
				"x": 141,
				"y": 146
			},
			"bl": {
				"x": 105,
				"y": 146
			}
		}
	],
	"hurtboxes": [
		{
			"tl": {
				"x": 25,
				"y": 22
			},
			"tr": {
				"x": 93,
				"y": 22
			},
			"br": {
				"x": 93,
				"y": 146
			},
			"bl": {
				"x": 25,
				"y": 146
			}
		},
		{
			"tl": {
				"x": 93,
				"y": 6
			},
			"tr": {
				"x": 149,
				"y": 6
			},
			"br": {
				"x": 149,
				"y": 146
			},
			"bl": {
				"x": 93,
				"y": 146
			}
		}
	]
}